scim2_tester/__init__.py
scim2_tester/checker.py
scim2_tester/checkers/__init__.py
scim2_tester/checkers/_discovery_utils.py
scim2_tester/checkers/misc.py
scim2_tester/checkers/patch_add.py
scim2_tester/checkers/patch_remove.py
scim2_tester/checkers/patch_replace.py
scim2_tester/checkers/resource.py
scim2_tester/checkers/resource_delete.py
scim2_tester/checkers/resource_get.py
scim2_tester/checkers/resource_post.py
scim2_tester/checkers/resource_put.py
scim2_tester/checkers/resource_types.py
scim2_tester/checkers/schemas.py
scim2_tester/checkers/service_provider_config.py
scim2_tester/cli.py
scim2_tester/discovery.py
scim2_tester/filling.py
scim2_tester/py.typed
scim2_tester/utils.py
scim2_tester-0.2.5.dist-info/WHEEL
scim2_tester-0.2.5.dist-info/METADATA
scim2_tester-0.2.5.dist-info/RECORD
